{"ID": 1, "Gateway Port": 16, "Gateway Number": 15, "Sender": "08123456789", "Message": "asdfasf", "Receive Date": "2023-11-26 13:34:08"}
{"ID": 1, "Gateway Port": 16, "Gateway Number": 15, "Sender": "08123456789", "Message": "asdfasf", "Receive Date": "2023-11-26 13:34:08"}
{"ID": 1, "Gateway Port": 16, "Gateway Number": 15, "Sender": "08123456789", "Message": "kk#sdfasfd", "Receive Date": "2023-11-26 13:34:08"}
{"ID": 1, "Gateway Port": 16, "Gateway Number": 15, "Sender": "08123456789", "Message": "kk#sdfasfd", "Receive Date": "2023-11-26 13:34:08"}
{"ID": 1, "Gateway Port": 16, "Gateway Number": 15, "Sender": "08123456789", "Message": "kk#sdfasfd", "Receive Date": "2023-11-26 13:34:08"}
{"ID": 1, "Gateway Port": 16, "Gateway Number": 15, "Sender": "08123456789", "Message": "kk#event#12#12#12", "Receive Date": "2023-11-26 13:34:08"}
{"ID": 1, "Gateway Port": 16, "Gateway Number": 15, "Sender": "08123456789", "Message": "kk#pilpres#12#12#12", "Receive Date": "2023-11-26 13:34:08"}
{"ID": 1, "Gateway Port": 16, "Gateway Number": 15, "Sender": "08123456789", "Message": "kk#EKB#pilpres#12#12#12", "Receive Date": "2023-11-26 13:34:08"}
{"ID": 1, "Gateway Port": 16, "Gateway Number": 15, "Sender": "08123456789", "Message": "kk#EKB#pilpres#12#12#12", "Receive Date": "2023-11-26 13:34:08"}
{"ID": 1, "Gateway Port": 16, "Gateway Number": 15, "Sender": "08123456789", "Message": "kk#EKB#pilpres#12#12#12", "Receive Date": "2023-11-26 13:34:08"}
{"ID": 1, "Gateway Port": 16, "Gateway Number": 15, "Sender": "08123456789", "Message": "kk#EKB#pilpres#12#12#12", "Receive Date": "2023-11-26 13:34:08"}
{"ID": 1, "Gateway Port": 16, "Gateway Number": 15, "Sender": "08123456789", "Message": "kk#EKB#pilpres#12#12#12", "Receive Date": "2023-11-26 13:34:08"}
{"ID": 1, "Gateway Port": 16, "Gateway Number": 15, "Sender": "08123456789", "Message": "kk#EKB#pilpres#12#12#12", "Receive Date": "2023-11-26 13:34:08"}
{"ID": 1, "Gateway Port": 16, "Gateway Number": 15, "Sender": "08123456789", "Message": "kk#EKB#pilpres#12#12#12", "Receive Date": "2023-11-26 13:34:08"}
{"ID": 1, "Gateway Port": 16, "Gateway Number": 15, "Sender": "08123456789", "Message": "kk#EKB#pilpres#12#12#12", "Receive Date": "2023-11-26 13:34:08"}
{"ID": 1, "Gateway Port": 16, "Gateway Number": 15, "Sender": "08123456789", "Message": "kk#EKB#pilpres#12#12#12", "Receive Date": "2023-11-26 13:34:08"}
{"ID": 1, "Gateway Port": 16, "Gateway Number": 15, "Sender": "08123456789", "Message": "kk#EKB#pilpres#12#12#12", "Receive Date": "2023-11-26 13:34:08"}
{"ID": 1, "Gateway Port": 16, "Gateway Number": 15, "Sender": "08123456789", "Message": "kk#shm#pilpres#12#12#12", "Receive Date": "2023-11-26 13:34:08"}
{"ID": 1, "Gateway Port": 16, "Gateway Number": 15, "Sender": "08123456789", "Message": "kk#shm#pilpres#12#12#12", "Receive Date": "2023-11-26 13:34:08"}
{"ID": 1, "Gateway Port": 16, "Gateway Number": 15, "Sender": "08123456789", "Message": "kk#shm#pilpres#12#12#12", "Receive Date": "2023-11-26 13:34:08"}
{"ID": 1, "Gateway Port": 16, "Gateway Number": 15, "Sender": "08123456789", "Message": "kk#shm#pilpres#12#12#12", "Receive Date": "2023-11-26 13:34:08"}
{"ID": 1, "Gateway Port": 16, "Gateway Number": 15, "Sender": "08123456789", "Message": "kk#shm#pilpres#12#12#12", "Receive Date": "2023-11-26 13:34:08"}
{"ID": 1, "Gateway Port": 16, "Gateway Number": 15, "Sender": "08123456789", "Message": "kk#shm#pilpres#12#12#12", "Receive Date": "2023-11-26 13:34:08"}
{"ID": 1, "Gateway Port": 16, "Gateway Number": 15, "Sender": "08123456789", "Message": "kk#shm#pilpres#12#12#12", "Receive Date": "2023-11-26 13:34:08"}
{"ID": 1, "Gateway Port": 16, "Gateway Number": 15, "Sender": "08123456789", "Message": "kk#shm#pilpres#12#12#12", "Receive Date": "2023-11-26 13:34:08"}
{"ID": 1, "Gateway Port": 16, "Gateway Number": 15, "Sender": "08123456789", "Message": "kk#shm#pilpres#12#12#12", "Receive Date": "2023-11-26 13:34:08"}
{"ID": 1, "Gateway Port": 16, "Gateway Number": 15, "Sender": "08123456789", "Message": "kk#shm#pilpres#12#12#12", "Receive Date": "2023-11-26 13:34:08"}
{"ID": 1, "Gateway Port": 16, "Gateway Number": 15, "Sender": "08123456789", "Message": "kk#shm#pilpres#12#12#12", "Receive Date": "2023-11-26 13:34:08"}
{"ID": 1, "Gateway Port": 16, "Gateway Number": 15, "Sender": "08123456789", "Message": "kk#shm#pilpres#52#72#32#2", "Receive Date": "2023-11-26 13:34:08"}
{"ID": 1, "Gateway Port": {}, "Gateway Number": 15, "Sender": "08123456789", "Message": "kk#shm#pilpres#52#72#32#2", "Receive Date": "2023-11-26 13:34:08"}
{"ID": 1, "Gateway Port": {}, "Gateway Number": 15, "Sender": "08123456789", "Message": "kk#shm#pilpres#52#72#32#2", "Receive Date": "2023-11-26 13:34:08"}
{"ID": 1, "Gateway Port": "/receive-1", "Gateway Number": 15, "Sender": "08123456789", "Message": "kk#shm#pilpres#52#72#32#2", "Receive Date": "2023-11-26 13:34:08"}
{"ID": 1, "Gateway Port": "1", "Gateway Number": 15, "Sender": "08123456789", "Message": "kk#shm#pilpres#52#72#32#2", "Receive Date": "2023-11-26 13:34:08"}
{"ID": 1, "Gateway Port": "1", "Gateway Number": 1234, "Sender": "08123456789", "Message": "kk#19k#pilpres#32#16#65#10", "Receive Date": "2023-11-26 13:34:08"}
{"ID": 1, "Gateway Port": "1", "Gateway Number": 1234, "Sender": "08123456789", "Message": "kk#19k#pilpres#32#16#65#10", "Receive Date": "2023-11-26 13:34:08"}
{"ID": 1, "Gateway Port": "1", "Gateway Number": 1234, "Sender": "08123456789", "Message": "kk#19k#pilpres#32#16#65#10", "Receive Date": "2023-11-26 13:34:08"}
{"ID": 1, "Gateway Port": "1", "Gateway Number": 1234, "Sender": "08123456789", "Message": "kk#19k#pilpres#32#16#65#10", "Receive Date": "2023-11-26 13:34:08"}
{"ID": 1, "Gateway Port": "1", "Gateway Number": 1234, "Sender": "08123456789", "Message": "kk#19k#pilpres#32#16#65#10", "Receive Date": "2023-11-26 13:34:08"}
{"ID": 1, "Gateway Port": "1", "Gateway Number": 1234, "Sender": "08123456789", "Message": "kk#19k#pilpres#32#16#65#10", "Receive Date": "2023-11-26 13:34:08"}
{"ID": 1, "Gateway Port": "1", "Gateway Number": 1234, "Sender": "08123456789", "Message": "kk#19k#pilpres#32#16#65#10", "Receive Date": "2023-11-26 13:34:08"}
{"ID": 1, "Gateway Port": "1", "Gateway Number": 1234, "Sender": "08123456789", "Message": "kk#19k#pilpres#32#16#65#10", "Receive Date": "2023-11-26 13:34:08"}
{"ID": 1, "Gateway Port": "1", "Gateway Number": 567, "Sender": "081111111", "Message": "kk#19k#pilpres#32#16#65", "Receive Date": "2023-11-26 03:34:08"}
{"ID": 1, "Gateway Port": "1", "Gateway Number": 567, "Sender": "081111111", "Message": "kk#19k#pilpres#32#16#65", "Receive Date": "2023-11-26 03:34:08"}
{"ID": 35, "Gateway Port": "1", "Gateway Number": 12, "Sender": "08333111", "Message": "kk#ijmoi;ajre", "Receive Date": "2023-11-26 00:00:01"}
{"ID": 35, "Gateway Port": "1", "Gateway Number": 12, "Sender": "08333111", "Message": "kk#6G7#pilpres#32#16#65", "Receive Date": "2023-11-26 00:00:01+0700"}
{"ID": 11123, "Gateway Port": "1", "Gateway Number": 1, "Sender": "08333111", "Message": "kasdflaskjdfasj;gi;aoijgo", "Receive Date": "2023-11-27 11:00:01+0700"}
{"ID": 11123, "Gateway Port": "1", "Gateway Number": 1, "Sender": "08333111", "Message": "kk#asdf'aspgjpmgb", "Receive Date": "2023-11-27 13:00:01+0700"}
{"ID": 11123, "Gateway Port": "1", "Gateway Number": 1, "Sender": "08333111", "Message": "kk#9U4#12#45#45", "Receive Date": "2023-11-27 13:00:01+0700"}
{"ID": 11123, "Gateway Port": "1", "Gateway Number": 1, "Sender": "08333111", "Message": "kk#9U4#pilpres#12#45#45", "Receive Date": "2023-11-27 13:00:01+0700"}
{"ID": 11123, "Gateway Port": "1", "Gateway Number": 1, "Sender": "08333111", "Message": "kk#k5c#pilpres#12#45#45", "Receive Date": "2023-11-27 13:00:01+0700"}
{"ID": 11123, "Gateway Port": "1", "Gateway Number": 1, "Sender": "08333111", "Message": "kk#k5c#pilpres#112#145#245#04", "Receive Date": "2023-11-27 13:00:01+0700"}
{"ID": 11123, "Gateway Port": "1", "Gateway Number": 1, "Sender": "08333111", "Message": "kk#k5c#pilpres#12#45#25#04", "Receive Date": "2023-11-27 13:00:01+0700"}
{"ID": 11123, "Gateway Port": "1", "Gateway Number": 1, "Sender": "08333111", "Message": "kk#k5c#pilpres#12#45#25#04", "Receive Date": "2023-11-27 13:00:01+0700"}
{"ID": 11123, "Gateway Port": "1", "Gateway Number": 1, "Sender": "08333111", "Message": "kk#k5c#pilpres#12#45#25#4", "Receive Date": "2023-11-27 13:00:01+0700"}
{"ID": 11123, "Gateway Port": "1", "Gateway Number": 1, "Sender": "08333111", "Message": "kk#k5c#pilpres#12#45#25#4", "Receive Date": "2023-11-27 13:00:01+0700"}
{"ID": 11123, "Gateway Port": "1", "Gateway Number": 1, "Sender": "08333111", "Message": "kk#k5c#pilpres#12#45#25#4", "Receive Date": "2023-11-27 13:00:01+0700"}
